{
  "bookshelves": [
    {
      "kind": "books#volume",
      "id": "pBIKPBAqmfAC",
      "etag": "dzr9YgZ+F30",
      "selfLink": "https://www.googleapis.com/books/v1/volumes/pBIKPBAqmfAC",
      "volumeInfo": {
        "title": "My Soccer Book",
        "authors": [
          "Gail Gibbons"
        ],
        "publisher": "Harper Collins",
        "publishedDate": "2000-03-01",
        "description": "Soccer is fun - let's play! Find all the basics in this lively guide. The markings on a soccer field What soccer players wear The positions, from forward to goalkeeper The excitement of pasing a ball The thrill of making a goal All these and more are included, with a useful glossary at the end.",
        "industryIdentifiers": [
          {
            "type": "ISBN_13",
            "identifier": "9780688171384"
          },
          {
            "type": "ISBN_10",
            "identifier": "0688171389"
          }
        ],
        "readingModes": {
          "text": false,
          "image": false
        },
        "pageCount": 24,
        "printType": "BOOK",
        "categories": [
          "Juvenile Nonfiction"
        ],
        "averageRating": 3,
        "ratingsCount": 2,
        "maturityRating": "NOT_MATURE",
        "allowAnonLogging": false,
        "contentVersion": "preview-1.0.0",
        "imageLinks": {
          "smallThumbnail": "http://books.google.com/books/content?id=pBIKPBAqmfAC&printsec=frontcover&img=1&zoom=5&edge=curl&source=gbs_api",
          "thumbnail": "http://books.google.com/books/content?id=pBIKPBAqmfAC&printsec=frontcover&img=1&zoom=1&edge=curl&source=gbs_api"
        },
        "language": "en",
        "previewLink": "http://books.google.com/books?id=pBIKPBAqmfAC&printsec=frontcover&dq=Soccer&hl=&cd=1&source=gbs_api",
        "infoLink": "http://books.google.com/books?id=pBIKPBAqmfAC&dq=Soccer&hl=&source=gbs_api",
        "canonicalVolumeLink": "https://books.google.com/books/about/My_Soccer_Book.html?hl=&id=pBIKPBAqmfAC"
      },
      "saleInfo": {
        "country": "US",
        "saleability": "NOT_FOR_SALE",
        "isEbook": false
      },
      "accessInfo": {
        "country": "US",
        "viewability": "PARTIAL",
        "embeddable": true,
        "publicDomain": false,
        "textToSpeechPermission": "ALLOWED_FOR_ACCESSIBILITY",
        "epub": {
          "isAvailable": false
        },
        "pdf": {
          "isAvailable": false
        },
        "webReaderLink": "http://play.google.com/books/reader?id=pBIKPBAqmfAC&hl=&printsec=frontcover&source=gbs_api",
        "accessViewStatus": "SAMPLE",
        "quoteSharingAllowed": false
      },
      "searchInfo": {
        "textSnippet": "Soccer is fun - let&#39;s play! Find all the basics in this lively guide."
      }
    }
  ]
}